{
    "country": "Romania",
    "country_code": "RO",
    "ISO_3166_1": { "name": "Romania" , "name_fr": "Roumanie (la)" , "alpha2": "RO" , "alpha3": "ROU" , "numeric": 642 },
    "list": [
{ "id": 1, "bank": "ACTIVE INTERNATIONAL SA", "city": "BUCHAREST", "branch": null, "swift_code": "ACIRROB1XXX" },
{ "id": 2, "bank": "ACTINVEST SA", "city": "BRASOV", "branch": null, "swift_code": "ACTNRO21XXX" },
{ "id": 3, "bank": "ALPHA FINANCE ROMANIA SA", "city": "BUCHAREST", "branch": null, "swift_code": "ALNRROB1XXX" },
{ "id": 4, "bank": "AUSTRO-ROM S.A.", "city": "BUCHAREST", "branch": null, "swift_code": "AUSMROB1XXX" },
{ "id": 5, "bank": "B.C.R. SECURITIES S.A.", "city": "BUCHAREST", "branch": null, "swift_code": "BCERROB1XXX" },
{ "id": 6, "bank": "BCR BANCA PENTRU LOCUINTE S.A.", "city": "BUCHAREST", "branch": null, "swift_code": "BCRLROBUXXX" },
{ "id": 7, "bank": "BANCA COMERCIALA FEROVIARA S.A.", "city": "BUCHAREST", "branch": null, "swift_code": "BFERROBUXXX" },
{ "id": 8, "bank": "BFOREX GLOBAL TRADING S.A.", "city": "BUCHAREST", "branch": null, "swift_code": "BGLTROB1XXX" },
{ "id": 9, "bank": "BLOM BANK FRANCE S.A. ROMANIA BRANCH", "city": "BUCHAREST", "branch": null, "swift_code": "BLOMROBUXXX" },
{ "id": 10, "bank": "BRD - GROUPE SOCIETE GENERALE SA", "city": "BUCHAREST", "branch": "(CAMPINEANU BRANCH)", "swift_code": "BRDEROBUCAM" },
{ "id": 11, "bank": "BRD - GROUPE SOCIETE GENERALE SA", "city": "BUCHAREST", "branch": "(SECURITIES DIVISION)", "swift_code": "BRDEROBUTIT" },
{ "id": 12, "bank": "LIBRA BANK S.A.", "city": "BUCHAREST", "branch": null, "swift_code": "BRELROBUCAM" },
{ "id": 13, "bank": "LIBRA BANK S.A.", "city": "BUCHAREST", "branch": null, "swift_code": "BRELROBUXXX" },
{ "id": 14, "bank": "BANCA ROMANEASCA S.A.", "city": "BUCHAREST", "branch": null, "swift_code": "BRMAROBUXXX" },
{ "id": 15, "bank": "CREDIT AGRICOLE BANK ROMANIA S.A.", "city": "BUCHAREST", "branch": null, "swift_code": "BSEAROBUXXX" },
{ "id": 16, "bank": "BRD SECURITIES-GROUPE SOCIETE GENERALE S.A.", "city": "BUCHAREST", "branch": null, "swift_code": "BSGSROB1XXX" },
{ "id": 17, "bank": "BANCA TRANSILVANIA S.A.", "city": "SEBES", "branch": "(SEBES BRANCH)", "swift_code": "BTRLRO21AB1" },
{ "id": 18, "bank": "BANCA TRANSILVANIA S.A.", "city": "BUCHAREST", "branch": "(ROSETTI BRANCH)", "swift_code": "BTRLRO21BBT" },
{ "id": 19, "bank": "BANCA TRANSILVANIA S.A.", "city": "ORADEA", "branch": "(AG. REPUBLICII)", "swift_code": "BTRLRO21BH1" },
{ "id": 20, "bank": "BANCA TRANSILVANIA S.A.", "city": "ORADEA", "branch": "(AG CANTEMIR)", "swift_code": "BTRLRO21BH2" },
{ "id": 21, "bank": "BANCA TRANSILVANIA S.A.", "city": "ORADEA", "branch": "(AG LOTUS)", "swift_code": "BTRLRO21BH3" },
{ "id": 22, "bank": "BANCA TRANSILVANIA S.A.", "city": "CLUJ-NAPOCA", "branch": "(AG. DOROBANTILOR)", "swift_code": "BTRLRO21CJ1" },
{ "id": 23, "bank": "BANCA TRANSILVANIA S.A.", "city": "CLUJ-NAPOCA", "branch": "(AG MANASTUR)", "swift_code": "BTRLRO21CJ2" },
{ "id": 24, "bank": "BANCA TRANSILVANIA S.A.", "city": "CLUJ-NAPOCA", "branch": "(AG BARITIU)", "swift_code": "BTRLRO21CJ3" },
{ "id": 25, "bank": "BANCA TRANSILVANIA S.A.", "city": "CLUJ-NAPOCA", "branch": "(ZORILOR BRANCH)", "swift_code": "BTRLRO21CJ4" },
{ "id": 26, "bank": "BANCA TRANSILVANIA S.A.", "city": "CLUJ-NAPOCA", "branch": "(GRIGORESCU BRANCH)", "swift_code": "BTRLRO21CJ5" },
{ "id": 27, "bank": "BANCA TRANSILVANIA S.A.", "city": "CLUJ-NAPOCA", "branch": "(MARASTI BRANCH)", "swift_code": "BTRLRO21CJ6" },
{ "id": 28, "bank": "BANCA TRANSILVANIA S.A.", "city": "CAMPIA TURZII", "branch": "(CAMPIA TURZII BRANCH)", "swift_code": "BTRLRO21CJ7" },
{ "id": 29, "bank": "BANCA TRANSILVANIA S.A.", "city": "GIURGIU", "branch": "(AG. GIURGIU)", "swift_code": "BTRLRO21GR1" },
{ "id": 30, "bank": "BANCA TRANSILVANIA S.A.", "city": "HUNEDOARA", "branch": "(AG HUNEDOARA)", "swift_code": "BTRLRO21HD1" },
{ "id": 31, "bank": "BANCA TRANSILVANIA S.A.", "city": "MIERCUREA CIUC", "branch": "(MIERCUREA CIUC BRANCH)", "swift_code": "BTRLRO21HRA" },
{ "id": 32, "bank": "BANCA TRANSILVANIA S.A.", "city": "TARGU MURES", "branch": "(TARGU MURES BRANCH)", "swift_code": "BTRLRO21MS1" },
{ "id": 33, "bank": "BANCA TRANSILVANIA S.A.", "city": "SIGHISOARA", "branch": "(SIGHISOARA BRANCH)", "swift_code": "BTRLRO21MS2" },
{ "id": 34, "bank": "BANCA TRANSILVANIA S.A.", "city": "CAMPINA", "branch": "(AG. CAMPINA)", "swift_code": "BTRLRO21PH1" },
{ "id": 35, "bank": "BANCA TRANSILVANIA S.A.", "city": "MEDIAS", "branch": "(MEDIAS BRANCH)", "swift_code": "BTRLRO21SB1" },
{ "id": 36, "bank": "BANCA TRANSILVANIA S.A.", "city": "SIBIU", "branch": "(SIBIU BRANCH)", "swift_code": "BTRLRO21SB2" },
{ "id": 37, "bank": "BANCA TRANSILVANIA S.A.", "city": "TULCEA", "branch": "(TULCEA BRANCH)", "swift_code": "BTRLRO21TLA" },
{ "id": 38, "bank": "BANCA TRANSILVANIA S.A.", "city": "ALBA IULIA", "branch": "(ALBA BRANCH)", "swift_code": "BTRLRO22ABA" },
{ "id": 39, "bank": "BANCA TRANSILVANIA S.A.", "city": "AIUD", "branch": "(AIUD)", "swift_code": "BTRLRO22ABI" },
{ "id": 40, "bank": "BANCA TRANSILVANIA S.A.", "city": "PITESTI", "branch": "(PITESTI BRANCH)", "swift_code": "BTRLRO22AGA" },
{ "id": 41, "bank": "BANCA TRANSILVANIA S.A.", "city": "ARAD", "branch": "(AG. ARAD)", "swift_code": "BTRLRO22AR1" },
{ "id": 42, "bank": "BANCA TRANSILVANIA S.A.", "city": "ARAD", "branch": "(AG. ARAD)", "swift_code": "BTRLRO22AR2" },
{ "id": 43, "bank": "BANCA TRANSILVANIA S.A.", "city": "NADLAC", "branch": "(AG. NADLAC)", "swift_code": "BTRLRO22AR3" },
{ "id": 44, "bank": "BANCA TRANSILVANIA S.A.", "city": "CHISINAU CRIS", "branch": "(AG. CHISINAU CRIS)", "swift_code": "BTRLRO22AR4" },
{ "id": 45, "bank": "BANCA TRANSILVANIA S.A.", "city": "INEU", "branch": "(AG. INEU)", "swift_code": "BTRLRO22AR5" },
{ "id": 46, "bank": "BANCA TRANSILVANIA S.A.", "city": "ARAD", "branch": "(ARAD BRANCH)", "swift_code": "BTRLRO22ARA" },
{ "id": 47, "bank": "BANCA TRANSILVANIA S.A.", "city": "BUCHAREST", "branch": "(MILITARI BRANCH)", "swift_code": "BTRLRO22BB1" },
{ "id": 48, "bank": "BANCA TRANSILVANIA S.A.", "city": "BUCHAREST", "branch": "(AG. MARRIOTT)", "swift_code": "BTRLRO22BB2" },
{ "id": 49, "bank": "BANCA TRANSILVANIA S.A.", "city": "BUCHAREST", "branch": "(AG. MAGHERU)", "swift_code": "BTRLRO22BB3" },
{ "id": 50, "bank": "BANCA TRANSILVANIA S.A.", "city": "BUCHAREST", "branch": "(AG. DOROBANTI)", "swift_code": "BTRLRO22BB4" },
{ "id": 51, "bank": "BANCA TRANSILVANIA S.A.", "city": "BUCHAREST", "branch": "(PIATA ALBA-IULIA BRANCH)", "swift_code": "BTRLRO22BBA" },
{ "id": 52, "bank": "BANCA TRANSILVANIA S.A.", "city": "BUCHAREST", "branch": "(OBOR BRANCH)", "swift_code": "BTRLRO22BBB" },
{ "id": 53, "bank": "BANCA TRANSILVANIA S.A.", "city": "BUCHAREST", "branch": "(BUCURESTI CHIBRIT)", "swift_code": "BTRLRO22BBC" },
{ "id": 54, "bank": "BANCA TRANSILVANIA S.A.", "city": "BUCHAREST", "branch": "(CENTRE NOUVEAU BRANCH)", "swift_code": "BTRLRO22BBL" },
{ "id": 55, "bank": "BANCA TRANSILVANIA S.A.", "city": "BUCHAREST", "branch": "(PANTELIMON BRANCH)", "swift_code": "BTRLRO22BBP" },
{ "id": 56, "bank": "BANCA TRANSILVANIA S.A.", "city": "BUCHAREST", "branch": "(VICTORIEI BRANCH)", "swift_code": "BTRLRO22BBV" },
{ "id": 57, "bank": "BANCA TRANSILVANIA S.A.", "city": "BACAU", "branch": "(BACAU BRANCH)", "swift_code": "BTRLRO22BCA" },
{ "id": 58, "bank": "BANCA TRANSILVANIA S.A.", "city": "ONESTI", "branch": "(ONESTI)", "swift_code": "BTRLRO22BCO" },
{ "id": 59, "bank": "BANCA TRANSILVANIA S.A.", "city": "ALESD", "branch": "(AG. ALESD)", "swift_code": "BTRLRO22BH4" },
{ "id": 60, "bank": "BANCA TRANSILVANIA S.A.", "city": "BEIUS", "branch": "(BEIUS)", "swift_code": "BTRLRO22BHB" },
{ "id": 61, "bank": "BANCA TRANSILVANIA S.A.", "city": "BISTRITA", "branch": "(BISTRITA BRANCH)", "swift_code": "BTRLRO22BNA" },
{ "id": 62, "bank": "BANCA TRANSILVANIA S.A.", "city": "BUCHAREST", "branch": "(BUCURESTI OTOPENI)", "swift_code": "BTRLRO22BOT" },
{ "id": 63, "bank": "BANCA TRANSILVANIA S.A.", "city": "BRAILA", "branch": "(BRAILA BRANCH)", "swift_code": "BTRLRO22BRA" },
{ "id": 64, "bank": "BANCA TRANSILVANIA S.A.", "city": "BOTOSANI", "branch": "(BOTOSANI)", "swift_code": "BTRLRO22BTA" },
{ "id": 65, "bank": "BANCA TRANSILVANIA S.A.", "city": "CLUJ-NAPOCA", "branch": "(BT SECURITIES)", "swift_code": "BTRLRO22BTS" },
{ "id": 66, "bank": "BANCA TRANSILVANIA S.A.", "city": "BRASOV", "branch": "(BRASOV BRANCH)", "swift_code": "BTRLRO22BVA" },
{ "id": 67, "bank": "BANCA TRANSILVANIA S.A.", "city": "FAGARAS", "branch": "(FAGARAS)", "swift_code": "BTRLRO22BVF" },
{ "id": 68, "bank": "BANCA TRANSILVANIA S.A.", "city": "BUCHAREST", "branch": "(BUCURESTI VOLUNTARI)", "swift_code": "BTRLRO22BVO" },
{ "id": 69, "bank": "BANCA TRANSILVANIA S.A.", "city": "BUZAU", "branch": "(BUZAU BRANCH)", "swift_code": "BTRLRO22BZA" },
{ "id": 70, "bank": "BANCA TRANSILVANIA S.A.", "city": "RAMNICU SARAT", "branch": "(RAMNICU SARAT)", "swift_code": "BTRLRO22BZR" },
{ "id": 71, "bank": "BANCA TRANSILVANIA S.A.", "city": "CLUJ-NAPOCA", "branch": "(AG. BILLA)", "swift_code": "BTRLRO22CJ8" },
{ "id": 72, "bank": "BANCA TRANSILVANIA S.A.", "city": "DEJ", "branch": "(DEJ BRANCH)", "swift_code": "BTRLRO22CJD" },
{ "id": 73, "bank": "BANCA TRANSILVANIA S.A.", "city": "GHERLA", "branch": "(GHERLA)", "swift_code": "BTRLRO22CJG" },
{ "id": 74, "bank": "BANCA TRANSILVANIA S.A.", "city": "HUEDIN", "branch": "(HUEDIN)", "swift_code": "BTRLRO22CJH" },
{ "id": 75, "bank": "BANCA TRANSILVANIA S.A.", "city": "CLUJ-NAPOCA", "branch": "(MARASTI)", "swift_code": "BTRLRO22CJM" },
{ "id": 76, "bank": "BANCA TRANSILVANIA S.A.", "city": "TURDA", "branch": "(TURDA BRANCH)", "swift_code": "BTRLRO22CJT" },
{ "id": 77, "bank": "BANCA TRANSILVANIA S.A.", "city": "CLUJ-NAPOCA", "branch": "(ZORILOR)", "swift_code": "BTRLRO22CJZ" },
{ "id": 78, "bank": "BANCA TRANSILVANIA S.A.", "city": "RESITA", "branch": "(RESITA)", "swift_code": "BTRLRO22CSA" },
{ "id": 79, "bank": "BANCA TRANSILVANIA S.A.", "city": "MANGALIA", "branch": "(AG. MANGALIA)", "swift_code": "BTRLRO22CTM" },
{ "id": 80, "bank": "BANCA TRANSILVANIA S.A.", "city": "SFANTU GHEORGHE", "branch": "(SFANTU GHEORGHE BRANCH)", "swift_code": "BTRLRO22CVA" },
{ "id": 81, "bank": "BANCA TRANSILVANIA S.A.", "city": "TARGU SECUIESC", "branch": "(AG. TG. SECUIESC)", "swift_code": "BTRLRO22CVT" },
{ "id": 82, "bank": "BANCA TRANSILVANIA S.A.", "city": "TARGOVISTE", "branch": "(DAMBOVITA BRANCH)", "swift_code": "BTRLRO22DBA" },
{ "id": 83, "bank": "BANCA TRANSILVANIA S.A.", "city": "CRAIOVA", "branch": "(CRAIOVA BRANCH)", "swift_code": "BTRLRO22DJA" },
{ "id": 84, "bank": "BANCA TRANSILVANIA S.A.", "city": "TARGU JIU", "branch": "(TG. JIU BRANCH)", "swift_code": "BTRLRO22GJA" },
{ "id": 85, "bank": "BANCA TRANSILVANIA S.A.", "city": "GALATI", "branch": "(GALATI BRANCH)", "swift_code": "BTRLRO22GLA" },
{ "id": 86, "bank": "BANCA TRANSILVANIA S.A.", "city": "TECUCI", "branch": "(TECUCI)", "swift_code": "BTRLRO22GLT" },
{ "id": 87, "bank": "BANCA TRANSILVANIA S.A.", "city": "GIURGIU", "branch": "(ZONA LIBERTA GIURGIU BRANCH)", "swift_code": "BTRLRO22GRA" },
{ "id": 88, "bank": "BANCA TRANSILVANIA S.A.", "city": "DEVA", "branch": "(DEVA BRANCH)", "swift_code": "BTRLRO22HDA" },
{ "id": 89, "bank": "BANCA TRANSILVANIA S.A.", "city": "PETROSANI", "branch": "(PETROSANI)", "swift_code": "BTRLRO22HDP" },
{ "id": 90, "bank": "BANCA TRANSILVANIA S.A.", "city": "ODORHEIU SECUIESC", "branch": "(ODORHEIU SECUIESC)", "swift_code": "BTRLRO22HRO" },
{ "id": 91, "bank": "BANCA TRANSILVANIA S.A.", "city": "SLOBOZIA", "branch": "(SLOBOZIA)", "swift_code": "BTRLRO22ILA" },
{ "id": 92, "bank": "BANCA TRANSILVANIA S.A.", "city": "IASI", "branch": "(IASI BRANCH)", "swift_code": "BTRLRO22ISA" },
{ "id": 93, "bank": "BANCA TRANSILVANIA S.A.", "city": "TURNU SEVERIN", "branch": "(MEHEDINTI BRANCH)", "swift_code": "BTRLRO22MHA" },
{ "id": 94, "bank": "BANCA TRANSILVANIA S.A.", "city": "BAIA MARE", "branch": "(BAIA MARE BRANCH)", "swift_code": "BTRLRO22MMA" },
{ "id": 95, "bank": "BANCA TRANSILVANIA S.A.", "city": "SIGHET", "branch": "(AG. SIGHET)", "swift_code": "BTRLRO22MMS" },
{ "id": 96, "bank": "BANCA TRANSILVANIA S.A.", "city": "TARGU MURES", "branch": "(MURES BRANCH)", "swift_code": "BTRLRO22MSA" },
{ "id": 97, "bank": "BANCA TRANSILVANIA S.A.", "city": "REGHIN", "branch": "(AG. REGHIN)", "swift_code": "BTRLRO22MSR" },
{ "id": 98, "bank": "BANCA TRANSILVANIA S.A.", "city": "PIATRA NEAMT", "branch": "(NEAMT BRANCH)", "swift_code": "BTRLRO22NTA" },
{ "id": 99, "bank": "BANCA TRANSILVANIA S.A.", "city": "ROMAN", "branch": "(AG. ROMAN)", "swift_code": "BTRLRO22NTR" },
{ "id": 100, "bank": "BANCA TRANSILVANIA S.A.", "city": "TARGU NEAMT", "branch": "(TARGU NEAMT)", "swift_code": "BTRLRO22NTT" },
{ "id": 101, "bank": "BANCA TRANSILVANIA S.A.", "city": "SLATINA", "branch": "(SLATINA)", "swift_code": "BTRLRO22OTA" },
{ "id": 102, "bank": "BANCA TRANSILVANIA S.A.", "city": "PLOIESTI", "branch": "(PLOIESTI BRANCH)", "swift_code": "BTRLRO22PHA" },
{ "id": 103, "bank": "BANCA TRANSILVANIA S.A.", "city": "SIBIU", "branch": "(SIBIU BRANCH)", "swift_code": "BTRLRO22SBA" },
{ "id": 104, "bank": "BANCA TRANSILVANIA S.A.", "city": "ZALAU", "branch": "(ZALAU BRANCH)", "swift_code": "BTRLRO22SJA" },
{ "id": 105, "bank": "BANCA TRANSILVANIA S.A.", "city": "SATU MARE", "branch": "(SATU MARE BRANCH)", "swift_code": "BTRLRO22SMA" },
{ "id": 106, "bank": "BANCA TRANSILVANIA S.A.", "city": "CAREI", "branch": "(AG. CAREI)", "swift_code": "BTRLRO22SMC" },
{ "id": 107, "bank": "BANCA TRANSILVANIA S.A.", "city": "SUCEAVA", "branch": "(SUCEAVA BRANCH)", "swift_code": "BTRLRO22SVA" },
{ "id": 108, "bank": "BANCA TRANSILVANIA S.A.", "city": "FALTICENI", "branch": "(FALTICENI)", "swift_code": "BTRLRO22SVF" },
{ "id": 109, "bank": "BANCA TRANSILVANIA S.A.", "city": "RADAUTI", "branch": "(AG. RADAUTI)", "swift_code": "BTRLRO22SVR" },
{ "id": 110, "bank": "BANCA TRANSILVANIA S.A.", "city": "VATRA DORNEI", "branch": "(VATRA DORNEI)", "swift_code": "BTRLRO22SVV" },
{ "id": 111, "bank": "BANCA TRANSILVANIA S.A.", "city": "TIMISOARA", "branch": "(TIMISOARA BRANCH)", "swift_code": "BTRLRO22TMA" },
{ "id": 112, "bank": "BANCA TRANSILVANIA S.A.", "city": "LUGOJ", "branch": "(AG. LUGOJ)", "swift_code": "BTRLRO22TML" },
{ "id": 113, "bank": "BANCA TRANSILVANIA S.A.", "city": "ALEXANDRIA", "branch": "(ALEXANDRIA)", "swift_code": "BTRLRO22TRA" },
{ "id": 114, "bank": "BANCA TRANSILVANIA S.A.", "city": "RAMNICU VALCEA", "branch": "(VALCEA BRANCH)", "swift_code": "BTRLRO22VLA" },
{ "id": 115, "bank": "BANCA TRANSILVANIA S.A.", "city": "DRAGASANI", "branch": "(DRAGASANI)", "swift_code": "BTRLRO22VLD" },
{ "id": 116, "bank": "BANCA TRANSILVANIA S.A.", "city": "FOCSANI", "branch": "(FOCSANI BRANCH)", "swift_code": "BTRLRO22VRA" },
{ "id": 117, "bank": "BUCURESTI GLOBAL INVEST S.A.", "city": "BUCHAREST", "branch": null, "swift_code": "BUGIROB1XXX" },
{ "id": 118, "bank": "PATRIA BANK S.A.", "city": "SIBIU", "branch": null, "swift_code": "CARPRO22XXX" },
{ "id": 119, "bank": "CAPITOL S.A.", "city": "BUCHAREST", "branch": null, "swift_code": "CATLROB1XXX" },
{ "id": 120, "bank": "UNICREDIT CA-IB SECURITIES SA", "city": "BUCHAREST", "branch": null, "swift_code": "CAUEROB1XXX" },
{ "id": 121, "bank": "CASA DE COMPENSARE BUCURESTI S.A.", "city": "BUCHAREST", "branch": null, "swift_code": "CCBUROB1XXX" },
{ "id": 122, "bank": "CEC BANK-S.A.", "city": "BUCHAREST", "branch": null, "swift_code": "CECEROBUXXX" },
{ "id": 123, "bank": "CENTRAL EUROPEAN INVESTMENTS S.A.", "city": "BUCHAREST", "branch": null, "swift_code": "CEENROB1XXX" },
{ "id": 124, "bank": "CITIBANK EUROPE PLC, DUBLIN-SUCURSALA ROMANIA", "city": "BUCHAREST", "branch": "(TARGET 2)", "swift_code": "CITIROBUTGT" },
{ "id": 125, "bank": "CITIBANK EUROPE PLC, DUBLIN-SUCURSALA ROMANIA", "city": "BUCHAREST", "branch": "(TRADE SERVICES DEPT.)", "swift_code": "CITIROBUTRD" },
{ "id": 126, "bank": "CITIBANK EUROPE PLC, DUBLIN-SUCURSALA ROMANIA", "city": "BUCHAREST", "branch": null, "swift_code": "CITIROBUXXX" },
{ "id": 127, "bank": "CITY INVEST S.A.", "city": "GALATI", "branch": null, "swift_code": "CIYIRO21XXX" },
{ "id": 128, "bank": "CONFIDENT INVEST BUCHAREST S.A.", "city": "BUCHAREST", "branch": null, "swift_code": "COIHROB1XXX" },
{ "id": 129, "bank": "CAPITAL FINANCIAL SERVICES SA", "city": "BUCHAREST", "branch": null, "swift_code": "CPFSROBUXXX" },
{ "id": 130, "bank": "KD CAPITAL MANAGEMENT S.A.", "city": "BUCHAREST", "branch": null, "swift_code": "CPMAROB1XXX" },
{ "id": 131, "bank": "BANCA CENTRALA COOPERATISTA CREDITCOOP", "city": "BUCHAREST", "branch": null, "swift_code": "CRCOROBUXXX" },
{ "id": 132, "bank": "CARPATICA INVEST SA", "city": "SIBIU", "branch": null, "swift_code": "CRNVRO21XXX" },
{ "id": 133, "bank": "CASA ROMANA DE COMPENSATIE S.A.", "city": "SIBIU", "branch": null, "swift_code": "CSRCRO21XXX" },
{ "id": 134, "bank": "BANK LEUMI ROMANIA S.A.", "city": "BRASOV", "branch": null, "swift_code": "DAFBRO22BRA" },
{ "id": 135, "bank": "BANK LEUMI ROMANIA S.A.", "city": "BUCHAREST", "branch": null, "swift_code": "DAFBRO22BUC" },
{ "id": 136, "bank": "BANK LEUMI ROMANIA S.A.", "city": "CLUJ-NAPOCA", "branch": null, "swift_code": "DAFBRO22CLU" },
{ "id": 137, "bank": "BANK LEUMI ROMANIA S.A.", "city": "CONSTANTA", "branch": null, "swift_code": "DAFBRO22CTA" },
{ "id": 138, "bank": "BANK LEUMI ROMANIA S.A.", "city": "ORADEA", "branch": null, "swift_code": "DAFBRO22ORA" },
{ "id": 139, "bank": "BANK LEUMI ROMANIA S.A.", "city": "TIMISOARA", "branch": null, "swift_code": "DAFBRO22TIM" },
{ "id": 140, "bank": "BANK LEUMI ROMANIA S.A.", "city": "BUCHAREST", "branch": null, "swift_code": "DAFBRO22XXX" },
{ "id": 141, "bank": "DEPOZITARUL CENTRAL S.A.", "city": "BUCHAREST", "branch": null, "swift_code": "DECNROBUXXX" },
{ "id": 142, "bank": "S.C. DEPOZITARUL SIBEX S.A.", "city": "SIBIU", "branch": null, "swift_code": "DESXRO21XXX" },
{ "id": 143, "bank": "DORINVEST S.A.", "city": "BUCHAREST", "branch": null, "swift_code": "DORNROB1XXX" },
{ "id": 144, "bank": "DELTA VALORI MOBILIARE (D.V.M.) S.A", "city": "BUCHAREST", "branch": null, "swift_code": "DVMDROB1XXX" },
{ "id": 145, "bank": "EUROBANK SECURITIES S.A.", "city": "BUCHAREST", "branch": null, "swift_code": "EFESROB1XXX" },
{ "id": 146, "bank": "MARFIN BANK (ROMANIA) S.A.", "city": "BUCHAREST", "branch": null, "swift_code": "EGNAROBXXXX" },
{ "id": 147, "bank": "EGNATIA SECURITIES S.A.", "city": "BUCHAREST", "branch": null, "swift_code": "EGNTROB1XXX" },
{ "id": 148, "bank": "ELDAINVEST S.A.", "city": "GALATI", "branch": null, "swift_code": "ELDARO21XXX" },
{ "id": 149, "bank": "EQUITY INVEST S.A.", "city": "BUCHAREST", "branch": null, "swift_code": "EQIVROB1XXX" },
{ "id": 150, "bank": "ESTEURO CAPITAL S.A.", "city": "BUCHAREST", "branch": null, "swift_code": "ESCPROB1XXX" },
{ "id": 151, "bank": "ESTINVEST S.A.", "city": "FOCSANI", "branch": null, "swift_code": "ESTIRO21XXX" },
{ "id": 152, "bank": "ETR ROMANIA", "city": "BUCHAREST", "branch": null, "swift_code": "ETRMROB1XXX" },
{ "id": 153, "bank": "ETEBA ROMANIA S.A.", "city": "BUCHAREST", "branch": null, "swift_code": "ETROROB1XXX" },
{ "id": 154, "bank": "EUROSAVAM S.A.", "city": "PLOIESTI", "branch": null, "swift_code": "EURVROB1XXX" },
{ "id": 155, "bank": "S.S.I.F. VIENNA INVESTMENT TRUST S.A.", "city": "BUCHAREST", "branch": null, "swift_code": "FIEFROB1XXX" },
{ "id": 156, "bank": "FINACO SECURITIES S.A.", "city": "BUCHAREST", "branch": null, "swift_code": "FIUEROB1XXX" },
{ "id": 157, "bank": "ROMEXTERRA FINANCE S.A", "city": "TARGU MURES", "branch": null, "swift_code": "FNCCRO21XXX" },
{ "id": 158, "bank": "CREDIT EUROPE BANK (ROMANIA) S.A.", "city": "BUCHAREST", "branch": null, "swift_code": "FNNBROBUXXX" },
{ "id": 159, "bank": "BNP PARIBAS S.A. PARIS SUCURSALA BUCURESTI", "city": "BUCHAREST", "branch": null, "swift_code": "FTSBROBUXXX" },
{ "id": 160, "bank": "G.I.F.-GRUPUL DE INTERMEDIERE FINANCIARA S.A.", "city": "BUCHAREST", "branch": null, "swift_code": "GGIFROB1XXX" },
{ "id": 161, "bank": "GLOBAL VALORI MOBILIARE S.A.", "city": "BUCHAREST", "branch": null, "swift_code": "GLVMROB1XXX" },
{ "id": 162, "bank": "GOLDRING S.A.", "city": "TARGU MURES", "branch": null, "swift_code": "GOLIRO21XXX" },
{ "id": 163, "bank": "HARINVEST S.A.", "city": "RAMNICU VALCEA", "branch": null, "swift_code": "HARIRO21XXX" },
{ "id": 164, "bank": "HTI VALORI MOBILIARE S.A.", "city": "BUCHAREST", "branch": null, "swift_code": "HTVMROB1XXX" },
{ "id": 165, "bank": "IEBA TRUST S.A.", "city": "BUCHAREST", "branch": null, "swift_code": "IETRROB1XXX" },
{ "id": 166, "bank": "IFB FINWEST S.A.", "city": "ARAD", "branch": null, "swift_code": "IFFNRO21XXX" },
{ "id": 167, "bank": "INTERFINBROK CORPORATION S.A.", "city": "CONSTANTA", "branch": null, "swift_code": "INAORO21XXX" },
{ "id": 168, "bank": "ING BANK N.V., BUCHAREST BRANCH", "city": "BUCHAREST", "branch": null, "swift_code": "INGBROBUXXX" },
{ "id": 169, "bank": "INTERDEALER CAPITAL INVEST S.A.", "city": "CLUJ-NAPOCA", "branch": null, "swift_code": "INLNRO21XXX" },
{ "id": 170, "bank": "INVEST TRUST S.A.", "city": "CRAIOVA", "branch": null, "swift_code": "INUTRO21XXX" },
{ "id": 171, "bank": "INTERCAPITAL INVEST S.A.", "city": "BUCHAREST", "branch": null, "swift_code": "ITINROB1XXX" },
{ "id": 172, "bank": "INTERVAM S.A.", "city": "BUCHAREST", "branch": null, "swift_code": "ITTRROB1XXX" },
{ "id": 173, "bank": "G.M. INVEST S.A.", "city": "BUCHAREST", "branch": null, "swift_code": "IVTEROB1XXX" },
{ "id": 174, "bank": "HB INVEST S.A.", "city": "BRASOV", "branch": null, "swift_code": "IVTSRO21XXX" },
{ "id": 175, "bank": "KIRA CREDITO AND CAUZIONI IFN S.A", "city": "IASI", "branch": null, "swift_code": "KCCFRO21XXX" },
{ "id": 176, "bank": "SWISS CAPITAL SA", "city": "BUCHAREST", "branch": null, "swift_code": "KSRSROB1XXX" },
{ "id": 177, "bank": "BANCA ROMANA DE CREDITE SI INVESTITII S.A.", "city": "BUCHAREST", "branch": null, "swift_code": "MINDROBUXXX" },
{ "id": 178, "bank": "PROCREDIT BANK S.A.", "city": "BUCHAREST", "branch": null, "swift_code": "MIROROBUXXX" },
{ "id": 179, "bank": "MUNTENIA GLOBAL INVEST S.A.", "city": "BUCHAREST", "branch": null, "swift_code": "MUGIROB1XXX" },
{ "id": 180, "bank": "NATIONAL BANK OF ROMANIA", "city": "BUCHAREST", "branch": null, "swift_code": "NBORROBPXXX" },
{ "id": 181, "bank": "NATIONAL BANK OF ROMANIA", "city": "BUCHAREST", "branch": null, "swift_code": "NBORROBUXXX" },
{ "id": 182, "bank": "NOVA INVEST S.A.", "city": "SATU MARE", "branch": null, "swift_code": "NOIVRO21XXX" },
{ "id": 183, "bank": "OLTENIA GRUP INVEST S.A.", "city": "CRAIOVA", "branch": null, "swift_code": "OLGIRO21XXX" },
{ "id": 184, "bank": "CAPA FINANCE IFN SA", "city": "BUCHAREST", "branch": null, "swift_code": "PATRROB1XXX" },
{ "id": 185, "bank": "PORSCHE BANK ROMANIA SA", "city": "VOLUNTARI", "branch": null, "swift_code": "PORLROBUXXX" },
{ "id": 186, "bank": "PRIME TRANSACTION S.A.", "city": "BUCHAREST", "branch": null, "swift_code": "PRTAROB1XXX" },
{ "id": 187, "bank": "RAIFFEISEN CAPITAL AND INVESTMENT S.A.", "city": "BUCHAREST", "branch": null, "swift_code": "RACIROB1XXX" },
{ "id": 188, "bank": "BANCA COMERCIALA ROMANA S.A", "city": "ARAD", "branch": "(ARAD BRANCH)", "swift_code": "RNCBROBUAR0" },
{ "id": 189, "bank": "BANCA COMERCIALA ROMANA S.A", "city": "RESITA", "branch": "(CARAS SEVERIN BRANCH)", "swift_code": "RNCBROBUCS0" },
{ "id": 190, "bank": "BANCA COMERCIALA ROMANA S.A", "city": "SFANTU GHEORGHE", "branch": "(COVASNA BRANCH)", "swift_code": "RNCBROBUCV0" },
{ "id": 191, "bank": "BANCA COMERCIALA ROMANA S.A", "city": "SLOBOZIA", "branch": "(IALOMITA BRANCH)", "swift_code": "RNCBROBUIL0" },
{ "id": 192, "bank": "ROINVEST BUCOVINA S.A.", "city": "SUCEAVA", "branch": null, "swift_code": "ROBURO21XXX" },
{ "id": 193, "bank": "ROMBELL SECURITIES S.A.", "city": "BUCHAREST", "branch": null, "swift_code": "ROECROB1XXX" },
{ "id": 194, "bank": "IDEA BANK SA", "city": "BUCHAREST", "branch": null, "swift_code": "ROINROBUXXX" },
{ "id": 195, "bank": "ROMCAPITAL S.A.", "city": "TIMIS", "branch": null, "swift_code": "ROMCRO21XXX" },
{ "id": 196, "bank": "ROMANIAN POST NATIONAL COMPANY", "city": "BUCHAREST", "branch": null, "swift_code": "RONCROB1XXX" },
{ "id": 197, "bank": "RAIFFEISEN BANCA PENTRU LOCUINTE S.A.", "city": "BUCHAREST", "branch": null, "swift_code": "RZBLROBUXXX" },
{ "id": 198, "bank": "URSUS BREWERIES SA", "city": "BUCHAREST", "branch": null, "swift_code": "SABMROB1XXX" },
{ "id": 199, "bank": "SAMSUNG ELECTRONICS ROMANIA SRL", "city": "VOLUNTARI", "branch": null, "swift_code": "SECTRO214B6" },
{ "id": 200, "bank": "SAMSUNG ELECTRONICS ROMANIA SRL", "city": "VOLUNTARI", "branch": null, "swift_code": "SECTRO21XXX" },
{ "id": 201, "bank": "BT SECURITIES S.A.", "city": "CLUJ-NAPOCA", "branch": null, "swift_code": "SEEERO21XXX" },
{ "id": 202, "bank": "SOCIETATE DE INVESTITII FINANCIARE BROKER S.A.", "city": "CLUJ-NAPOCA", "branch": null, "swift_code": "SIFKRO21XXX" },
{ "id": 203, "bank": "NHL SECURITIES S.A.", "city": "BUCHAREST", "branch": null, "swift_code": "SMRSROB1XXX" },
{ "id": 204, "bank": "SOCIETATEA NATIONALA DE COMPENSARE, DECONTARE SI DEPOZITARE PENTRU VALORI MOBILIARE SA", "city": "BUCHAREST", "branch": null, "swift_code": "SNCDROB1XXX" },
{ "id": 205, "bank": "S.S.I.F. PIRAEUS SECURITIES ROMANIA S.A.", "city": "BUCHAREST", "branch": null, "swift_code": "SPSMROB1XXX" },
{ "id": 206, "bank": "SPEED TRANSFER FINANCIAR SRL", "city": "BUCHAREST", "branch": null, "swift_code": "SRFSROB1XXX" },
{ "id": 207, "bank": "S.S.I.F. FORTIUS FINANCE S.A.", "city": "BUCHAREST", "branch": null, "swift_code": "SSFIROB1XXX" },
{ "id": 208, "bank": "SSIF MOBINVEST S.A.", "city": "ORADEA", "branch": null, "swift_code": "SSMORO21XXX" },
{ "id": 209, "bank": "S.S.I.F. ORIZONT VEST S.A.", "city": "ORADEA", "branch": null, "swift_code": "SSOVRO21XXX" },
{ "id": 210, "bank": "SUPER GOLD INVEST S.A.", "city": "PITESTI", "branch": null, "swift_code": "SUGIRO21XXX" },
{ "id": 211, "bank": "TARGET CAPITAL S.A.", "city": "CLUJ-NAPOCA", "branch": null, "swift_code": "TACIRO21XXX" },
{ "id": 212, "bank": "TBI BANK EAD SOFIA BUCHAREST BRANCH", "city": "BUCHAREST", "branch": null, "swift_code": "TBIBROBUXXX" },
{ "id": 213, "bank": "TREND S.A.", "city": "BACAU", "branch": null, "swift_code": "TEENRO21XXX" },
{ "id": 214, "bank": "T.G.H. INVESTMENT S.A.", "city": "IASI", "branch": null, "swift_code": "TGINRO21XXX" },
{ "id": 215, "bank": "MINISTRY OF PUBLIC FINANCE", "city": "BUCHAREST", "branch": null, "swift_code": "TREZROBUXXX" },
{ "id": 216, "bank": "TRANSFOND S.A.", "city": "BUCHAREST", "branch": null, "swift_code": "TRFDROBSXXX" },
{ "id": 217, "bank": "BLUE ROCK FINANCIAL SERVICES", "city": "BUCHAREST", "branch": null, "swift_code": "TRPTRO21XXX" },
{ "id": 218, "bank": "UNICAPITAL S.A.", "city": "BUCHAREST", "branch": null, "swift_code": "UNCPROB1XXX" },
{ "id": 219, "bank": "FAIRWIND SECURITIES S.A.", "city": "BUCHAREST", "branch": null, "swift_code": "UNSUROB1XXX" },
{ "id": 220, "bank": "ARCELORMITTAL TUBULAR PRODUCTS ROMAN SA", "city": "GALATI", "branch": null, "swift_code": "USINRO21GAL" },
{ "id": 221, "bank": "ARCELORMITTAL TUBULAR PRODUCTS ROMAN SA", "city": "IASI", "branch": null, "swift_code": "USINRO21IAS" },
{ "id": 222, "bank": "ARCELORMITTAL TUBULAR PRODUCTS ROMAN SA", "city": "ROMAN", "branch": null, "swift_code": "USINRO21MSR" },
{ "id": 223, "bank": "ARCELORMITTAL TUBULAR PRODUCTS ROMAN SA", "city": "ROMAN", "branch": null, "swift_code": "USINRO21XXX" },
{ "id": 224, "bank": "VALAHIA CAPITAL SA", "city": "BUCHAREST", "branch": null, "swift_code": "VACTROB1XXX" },
{ "id": 225, "bank": "VALMOB INTERMEDIA S.A.", "city": "PITESTI", "branch": null, "swift_code": "VAITRO21XXX" },
{ "id": 226, "bank": "TRADEVILLE SA", "city": "BUCHAREST", "branch": null, "swift_code": "VANGROB1XXX" },
{ "id": 227, "bank": "VENTRUST INVESTMENT S.A.", "city": "TARGU MURES", "branch": null, "swift_code": "VEIVRO21XXX" },
{ "id": 228, "bank": "VOLTINVEST S.A.", "city": "CRAIOVA", "branch": null, "swift_code": "VOLTRO21XXX" },
{ "id": 229, "bank": "INTESA SANPAOLO ROMANIA S.A.", "city": "BUCHAREST", "branch": null, "swift_code": "WBANRO22XXX" },
{ "id": 230, "bank": "W.B.S. ROMANIA S.A.", "city": "BUCHAREST", "branch": null, "swift_code": "WBROROB1XXX" },
{ "id": 231, "bank": "BURSA DE VALORI BUCURESTI SA", "city": "BUCHAREST", "branch": null, "swift_code": "XBSEROB1XXX" },
{ "id": 232, "bank": "RASDAQ", "city": "BUCHAREST", "branch": null, "swift_code": "XRASROB1XXX" },
{ "id": 233, "bank": "ALIOR BANK SA WARSAW BUCHAREST BRANCH", "city": "BUCHAREST", "branch": null, "swift_code": "ALBPROBUXXX" },
{ "id": 234, "bank": "UNICREDIT BANK SA", "city": "BUCHAREST", "branch": null, "swift_code": "BACXROBUXXX" },
{ "id": 235, "bank": "BRD - GROUPE SOCIETE GENERALE SA", "city": "BUCHAREST", "branch": null, "swift_code": "BRDEROBUXXX" },
{ "id": 236, "bank": "BANCA TRANSILVANIA S.A.", "city": "CLUJ-NAPOCA", "branch": null, "swift_code": "BTRLRO22XXX" },
{ "id": 237, "bank": "BANCA TRANSILVANIA S.A.", "city": "ORADEA", "branch": "(ORADEA BRANCH)", "swift_code": "BTRLRO22BHA" },
{ "id": 238, "bank": "BANCA TRANSILVANIA S.A.", "city": "CLUJ-NAPOCA", "branch": "(CLUJ-NAPOCA BRANCH)", "swift_code": "BTRLRO22CJA" },
{ "id": 239, "bank": "BANCA TRANSILVANIA S.A.", "city": "CONSTANTA", "branch": "(CONSTANTA BRANCH)", "swift_code": "BTRLRO22CTA" },
{ "id": 240, "bank": "OTP BANK ROMANIA S.A.", "city": "BUCHAREST", "branch": null, "swift_code": "OTPVROBUXXX" },
{ "id": 241, "bank": "FIRST BANK", "city": "BUCHAREST", "branch": null, "swift_code": "PIRBROBUXXX" },
{ "id": 242, "bank": "BANCA COMERCIALA ROMANA S.A", "city": "BUCHAREST", "branch": null, "swift_code": "RNCBROBUXXX" },
{ "id": 243, "bank": "TRANSFOND S.A.", "city": "BUCHAREST", "branch": "(BACK OFFICE APPLICATION)", "swift_code": "TRFDROBSSNT" },
{ "id": 244, "bank": "GARANTI BANK S.A.", "city": "BUCHAREST", "branch": null, "swift_code": "UGBIROBUXXX" },
{ "id": 245, "bank": "ALPHA BANK ROMANIA SA", "city": "BUCHAREST", "branch": null, "swift_code": "BUCUROBUXXX" },
{ "id": 246, "bank": "EASTERN SECURITIES S.A.", "city": "BUCHAREST", "branch": null, "swift_code": "EASCROB1XXX" },
{ "id": 247, "bank": "EXIMBANK OF ROMANIA", "city": "BUCHAREST", "branch": null, "swift_code": "EXIMROBUXXX" },
{ "id": 248, "bank": "KMG ROMPETROL", "city": "BUCHAREST", "branch": null, "swift_code": "KMGRROBUXXX" },
{ "id": 249, "bank": "NATIONAL BANK OF ROMANIA - REGIS", "city": "BUCHAREST", "branch": null, "swift_code": "NBORROBAXXX" },
{ "id": 250, "bank": "NATIONAL BANK OF ROMANIA - SAFIR", "city": "BUCHAREST", "branch": null, "swift_code": "NBORROBBXXX" },
{ "id": 251, "bank": "ORANGE MONEY IFN SA", "city": "BUCHAREST", "branch": null, "swift_code": "ORMFROB1XXX" },
{ "id": 252, "bank": "RAIFFEISEN BANK S.A.", "city": "BUCHAREST", "branch": null, "swift_code": "RZBRROBUXXX" },
{ "id": 253, "bank": "S.S.I.F. ROMINTRADE S.A.", "city": "BRASOV", "branch": null, "swift_code": "SSRORO21XXX" },
{ "id": 254, "bank": "SC SMITH AND SMITH SRL", "city": "BUCHAREST", "branch": null, "swift_code": "SSRRROB1XXX" },
{ "id": 255, "bank": "SSIF STK TRADING S.A.", "city": "ARAD", "branch": null, "swift_code": "SSSRRO21XXX" },
{ "id": 256, "bank": "BURSA ROMANA DE MARFURI (ROMANIAN COMMODITIES EXCHANGE) SA", "city": "BUCHAREST", "branch": null, "swift_code": "BURMROB1XXX" },
{ "id": 257, "bank": "MONDIAL SA", "city": "LUGOJ", "branch": null, "swift_code": "MODLRO21XXX" },
{ "id": 258, "bank": "OMV PETROM SA", "city": "BUCHAREST", "branch": null, "swift_code": "OMVPROBBXXX" },
{ "id": 259, "bank": "BANK OF CHINA (HUNGARY) CLOSE LTD BUDAPESTA BUCHAREST BRANCH", "city": "BUCHAREST", "branch": null, "swift_code": "BKCHROBUXXX" },
{ "id": 260, "bank": "TRANSFER RAPID ELECTRONIC", "city": "BUCHAREST", "branch": null, "swift_code": "TRPCROB2XXX" },
{ "id": 261, "bank": "VIVA PAYMENT SERVICES S.A SUCURSALA BUCURESTI", "city": "BUCHAREST", "branch": null, "swift_code": "VPAYROB2XXX" },
{ "id": 262, "bank": "DEK-CO (UK) LIMITED SUCURSALA BUCURESTI", "city": "BUCHAREST", "branch": null, "swift_code": "DEUEROB1XXX" },
{ "id": 263, "bank": "A1 TELECOM NETWORK ISP SRL", "city": "BUCHAREST", "branch": null, "swift_code": "TNISROB2XXX" }
    ]
}
