{
    "country": "Tanzania",
    "country_code": "TZ",
    "ISO_3166_1": { "name": "Tanzania, United Republic of" , "name_fr": "Tanzanie, République-Unie de" , "alpha2": "TZ" , "alpha3": "TZA" , "numeric": 834 },
    "list": [
{ "id": 1, "bank": "ACCESSBANK TANZANIA LTD", "city": "DAR ES SALAAM", "branch": null, "swift_code": "ACTZTZTZXXX" },
{ "id": 2, "bank": "ADVANS BANK TANZANIA", "city": "DAR ES SALAAM", "branch": null, "swift_code": "ADVBTZTZXXX" },
{ "id": 3, "bank": "EAST AFRICAN DEVELOPMENT BANK", "city": "DAR ES SALAAM", "branch": null, "swift_code": "AFDETZT1XXX" },
{ "id": 4, "bank": "AKIBA COMMERCIAL BANK PLC", "city": "DAR ES SALAAM", "branch": null, "swift_code": "AKCOTZTZXXX" },
{ "id": 5, "bank": "AMANA BANK LIMITED", "city": "DAR ES SALAAM", "branch": null, "swift_code": "AMNNTZTZXXX" },
{ "id": 6, "bank": "AZANIA BANK LIMITED", "city": "DAR ES SALAAM", "branch": null, "swift_code": "AZANTZTZXXX" },
{ "id": 7, "bank": "BANK OF BARODA (TANZANIA) LTD", "city": "DAR ES SALAAM", "branch": null, "swift_code": "BARBTZTZXXX" },
{ "id": 8, "bank": "BARCLAYS BANK TANZANIA LTD", "city": "DAR ES SALAAM", "branch": null, "swift_code": "BARCTZTZXXX" },
{ "id": 9, "bank": "BANK OF INDIA (TANZANIA) LIMITED", "city": "DAR ES SALAAM", "branch": null, "swift_code": "BKIDTZTZXXX" },
{ "id": 10, "bank": "INTERNATIONAL COMMERCIAL BANK (TANZANIA) LIMITED", "city": "DAR ES SALAAM", "branch": null, "swift_code": "BKMYTZTZXXX" },
{ "id": 11, "bank": "BANK M TANZANIA PLC", "city": "DAR ES SALAAM", "branch": null, "swift_code": "BNKMTZTZXXX" },
{ "id": 12, "bank": "COMMERCIAL BANK OF AFRICA (TANZANIA) LTD", "city": "DAR ES SALAAM", "branch": null, "swift_code": "CBAFTZTZXXX" },
{ "id": 13, "bank": "CROWN FINANCE AND LEASING LIMITED", "city": "DAR ES SALAAM", "branch": null, "swift_code": "CFLLTZT1XXX" },
{ "id": 14, "bank": "CHINA COMMERCIAL BANK LIMITED", "city": "DAR ES SALAAM", "branch": null, "swift_code": "CHLMTZTZXXX" },
{ "id": 15, "bank": "CITIBANK TANZANIA LTD", "city": "DAR ES SALAAM", "branch": null, "swift_code": "CITITZTZXXX" },
{ "id": 16, "bank": "CRDB BANK LIMITED", "city": "DAR ES SALAAM", "branch": "(LUMUMBA BRANCH)", "swift_code": "CORUTZT10T2" },
{ "id": 17, "bank": "CRDB BANK LIMITED", "city": "TANGA", "branch": null, "swift_code": "CORUTZT10T3" },
{ "id": 18, "bank": "CRDB BANK LIMITED", "city": "ARUSHA", "branch": null, "swift_code": "CORUTZT10T4" },
{ "id": 19, "bank": "CRDB BANK LIMITED", "city": "MWANZA", "branch": null, "swift_code": "CORUTZT10T5" },
{ "id": 20, "bank": "CRDB BANK LIMITED", "city": "SHINYANGA", "branch": null, "swift_code": "CORUTZT10T6" },
{ "id": 21, "bank": "CRDB BANK LIMITED", "city": "DAR ES SALAAM", "branch": "(AZIKIWE BRANCH)", "swift_code": "CORUTZT10TD" },
{ "id": 22, "bank": "CRDB BANK LIMITED", "city": "DAR ES SALAAM", "branch": null, "swift_code": "CORUTZTZXXX" },
{ "id": 23, "bank": "DAR ES SALAAM COMMUNITY BANK LTD", "city": "DAR ES SALAAM", "branch": null, "swift_code": "DASUTZTZXXX" },
{ "id": 24, "bank": "DAR ES SALAAM STOCK EXCHANGE", "city": "DAR ES SALAAM", "branch": null, "swift_code": "DSTXTZTZXXX" },
{ "id": 25, "bank": "DIAMOND TRUST BANK TANZANIA LTD", "city": "DAR ES SALAAM", "branch": null, "swift_code": "DTKETZTZXXX" },
{ "id": 26, "bank": "ECOBANK TANZANIA LIMITED", "city": "DAR ES SALAAM", "branch": null, "swift_code": "ECOCTZTZXXX" },
{ "id": 27, "bank": "EQUITY BANK TANZANIA LIMITED", "city": "DAR ES SALAAM", "branch": null, "swift_code": "EQBLTZTZXXX" },
{ "id": 28, "bank": "EXIMBANK (TANZANIA) LTD", "city": "DAR ES SALAAM", "branch": null, "swift_code": "EXTNTZTZXXX" },
{ "id": 29, "bank": "FIRST NATIONAL BANK OF TANZANIA", "city": "DAR ES SALAAM", "branch": null, "swift_code": "FIRNTZTXXXX" },
{ "id": 30, "bank": "AFRICAN BANKING CORPORATION TANZANIA LIMITED", "city": "DAR ES SALAAM", "branch": null, "swift_code": "FMBZTZTXXXX" },
{ "id": 31, "bank": "HABIB AFRICAN BANK", "city": "DAR ES SALAAM", "branch": null, "swift_code": "HABLTZTZXXX" },
{ "id": 32, "bank": "I AND M BANK (T) LIMITED", "city": "DAR ES SALAAM", "branch": null, "swift_code": "IMBLTZTZXXX" },
{ "id": 33, "bank": "KARADHA COMPANY LTD", "city": "DAR ES SALAAM", "branch": null, "swift_code": "KACLTZT1XXX" },
{ "id": 34, "bank": "KCB BANK TANZANIA LIMITED", "city": "DAR ES SALAAM", "branch": null, "swift_code": "KCBLTZTZXXX" },
{ "id": 35, "bank": "KILIMANJARO CO-OPERATIVE BANK LTD", "city": "MOSHI", "branch": null, "swift_code": "KLMJTZTZXXX" },
{ "id": 36, "bank": "MAENDELEO BANK LTD", "city": "DAR ES SALAAM", "branch": null, "swift_code": "MBTLTZTZXXX" },
{ "id": 37, "bank": "MKOMBOZI COMMERCIAL BANK LTD", "city": "DAR ES SALAAM", "branch": null, "swift_code": "MKCBTZTZXXX" },
{ "id": 38, "bank": "MUCOBA BANK PLC", "city": "IRINGA", "branch": null, "swift_code": "MUOBTZTZXXX" },
{ "id": 39, "bank": "MWANGA COMMUNITY BANK LTD", "city": "MOSHI", "branch": null, "swift_code": "MWCBTZTZXXX" },
{ "id": 40, "bank": "MWALIMU COMMERCIAL BANK PLC", "city": "DAR ES SALAAM", "branch": null, "swift_code": "MWCOTZTZXXX" },
{ "id": 41, "bank": "NATIONAL BANK OF COMMERCE, THE", "city": "DAR ES SALAAM", "branch": "(BANK HOUSE BRANCH)", "swift_code": "NLCBTZT10T6" },
{ "id": 42, "bank": "NATIONAL BANK OF COMMERCE, THE", "city": "DAR ES SALAAM", "branch": "(MASDO HOUSE BRANCH)", "swift_code": "NLCBTZT10T7" },
{ "id": 43, "bank": "NATIONAL BANK OF COMMERCE, THE", "city": "DAR ES SALAAM", "branch": "(CORPORATE BRANCH)", "swift_code": "NLCBTZTX0T3" },
{ "id": 44, "bank": "NATIONAL BANK OF COMMERCE, THE", "city": "ARUSHA", "branch": "(ARUSHA BRANCH)", "swift_code": "NLCBTZTX0T4" },
{ "id": 45, "bank": "NATIONAL BANK OF COMMERCE, THE", "city": "MWANZA", "branch": "(MWANZA BRANCH)", "swift_code": "NLCBTZTX0T5" },
{ "id": 46, "bank": "NATIONAL BANK OF COMMERCE, THE", "city": "DAR ES SALAAM", "branch": "(SAMORA BRANCH)", "swift_code": "NLCBTZTX0T8" },
{ "id": 47, "bank": "NATIONAL BANK OF COMMERCE, THE", "city": "MOSHI", "branch": "(MOSHI BRANCH)", "swift_code": "NLCBTZTX0TM" },
{ "id": 48, "bank": "NATIONAL BANK OF COMMERCE, THE", "city": "DAR ES SALAAM", "branch": "(FINANCIAL DEPARTMENT-NBC HOUSE)", "swift_code": "NLCBTZTXFIN" },
{ "id": 49, "bank": "NATIONAL BANK OF COMMERCE, THE", "city": "DAR ES SALAAM", "branch": "(INDUSTRIAL BRANCH)", "swift_code": "NLCBTZTXIND" },
{ "id": 50, "bank": "NATIONAL BANK OF COMMERCE, THE", "city": "DAR ES SALAAM", "branch": "(KICHWELE BRANCH)", "swift_code": "NLCBTZTXKIC" },
{ "id": 51, "bank": "NATIONAL BANK OF COMMERCE, THE", "city": "MBEYA", "branch": "(MBEYA BRANCH)", "swift_code": "NLCBTZTXMBE" },
{ "id": 52, "bank": "NATIONAL BANK OF COMMERCE, THE", "city": "DAR ES SALAAM", "branch": "(MNAZI MMOJA BRANCH)", "swift_code": "NLCBTZTXMNA" },
{ "id": 53, "bank": "NATIONAL BANK OF COMMERCE, THE", "city": "MOROGORO", "branch": "(MOROGORO BRANCH)", "swift_code": "NLCBTZTXMOR" },
{ "id": 54, "bank": "NATIONAL BANK OF COMMERCE, THE", "city": "TANGA", "branch": "(TANGA BRANCH)", "swift_code": "NLCBTZTXTAN" },
{ "id": 55, "bank": "NATIONAL BANK OF COMMERCE, THE", "city": "DAR ES SALAAM", "branch": null, "swift_code": "NLCBTZTXXXX" },
{ "id": 56, "bank": "NATIONAL BANK OF COMMERCE, THE", "city": "ZANZIBAR", "branch": "(ZANZIBAR BRANCH-UNGUJA)", "swift_code": "NLCBTZTXZAN" },
{ "id": 57, "bank": "NMB BANK PLC", "city": "DAR ES SALAAM", "branch": null, "swift_code": "NMIBTZTZXXX" },
{ "id": 58, "bank": "ORBIT SECURITES CO LTD", "city": "DAR ES SALAAM", "branch": null, "swift_code": "ORSUTZT1XXX" },
{ "id": 59, "bank": "PEOPLE'S BANK OF ZANZIBAR, THE", "city": "ZANZIBAR", "branch": "(CHAKE CHAKE BRANCH)", "swift_code": "PBZATZTZCHK" },
{ "id": 60, "bank": "PEOPLE'S BANK OF ZANZIBAR, THE", "city": "ZANZIBAR", "branch": "(MWANAKWEREKWE BRANCH)", "swift_code": "PBZATZTZNWK" },
{ "id": 61, "bank": "PEOPLE'S BANK OF ZANZIBAR, THE", "city": "ZANZIBAR", "branch": null, "swift_code": "PBZATZTZXXX" },
{ "id": 62, "bank": "STANBIC BANK TANZANIA LIMITED", "city": "DAR ES SALAAM", "branch": null, "swift_code": "SBICTZTXXXX" },
{ "id": 63, "bank": "STATE BANK OF INDIA", "city": "DAR ES SALAAM", "branch": null, "swift_code": "SBINTZT1XXX" },
{ "id": 64, "bank": "STANDARD CHARTERED BANK TANZANIA LTD", "city": "DAR ES SALAAM", "branch": "(SECURITIES SERVICES UNIT)", "swift_code": "SCBLTZTXSSU" },
{ "id": 65, "bank": "NIC BANK (TANZANIA) LIMITED", "city": "DAR ES SALAAM", "branch": null, "swift_code": "SFICTZTZXXX" },
{ "id": 66, "bank": "TANZANIA HOUSING BANK", "city": "DAR ES SALAAM", "branch": "(HIFADHI BRANCH)", "swift_code": "TAHOTZT10T2" },
{ "id": 67, "bank": "TANZANIA HOUSING BANK", "city": "TANGA", "branch": "(TANGA BRANCH)", "swift_code": "TAHOTZT10T3" },
{ "id": 68, "bank": "TANZANIA HOUSING BANK", "city": "DODOMA", "branch": "(DODOMA BRANCH)", "swift_code": "TAHOTZT10T4" },
{ "id": 69, "bank": "TANZANIA HOUSING BANK", "city": "MWANZA", "branch": "(MWANZA BRANCH)", "swift_code": "TAHOTZT10T5" },
{ "id": 70, "bank": "TANZANIA HOUSING BANK", "city": "MBEYA", "branch": "(MBEYA BRANCH)", "swift_code": "TAHOTZT10T6" },
{ "id": 71, "bank": "TANZANIA HOUSING BANK", "city": "MOROGORO", "branch": "(MOROGORO BRANCH)", "swift_code": "TAHOTZT10T7" },
{ "id": 72, "bank": "TANZANIA HOUSING BANK", "city": "MOSHI", "branch": "(MOSHI BRANCH)", "swift_code": "TAHOTZT10T8" },
{ "id": 73, "bank": "TANZANIA HOUSING BANK", "city": "ZANZIBAR", "branch": "(ZANZIBAR BRANCH)", "swift_code": "TAHOTZT10TA" },
{ "id": 74, "bank": "TANZANIA HOUSING BANK", "city": "DAR ES SALAAM", "branch": null, "swift_code": "TAHOTZT1XXX" },
{ "id": 75, "bank": "TIB CORPORATE BANK LIMITED", "city": "DAR ES SALAAM", "branch": null, "swift_code": "TAINTZTZXXX" },
{ "id": 76, "bank": "BANK OF TANZANIA", "city": "DAR ES SALAAM", "branch": null, "swift_code": "TANZTZTXXXX" },
{ "id": 77, "bank": "TPB BANK PLC", "city": "DAR ES SALAAM", "branch": null, "swift_code": "TAPBTZTZXXX" },
{ "id": 78, "bank": "TANZANIA REVENUE AUTHORITY", "city": "DAR ES SALAAM", "branch": null, "swift_code": "TARATZTZXXX" },
{ "id": 79, "bank": "TRUST BANK (TANZANIA) LIMITED", "city": "DAR ES SALAAM", "branch": null, "swift_code": "TRBATZT1XXX" },
{ "id": 80, "bank": "UCHUMI COMMERCIAL BANK LTD", "city": "MOSHI", "branch": null, "swift_code": "UCCTTZTZXXX" },
{ "id": 81, "bank": "ULC (TANZANIA) LTD", "city": "DAR ES SALAAM", "branch": null, "swift_code": "ULCTTZT1XXX" },
{ "id": 82, "bank": "UNITED BANK FOR AFRICA (TANZANIA) LIMITED", "city": "DAR ES SALAAM", "branch": null, "swift_code": "UNAFTZTZXXX" },
{ "id": 83, "bank": "UBL BANK (TANZANIA) LIMITED", "city": "DAR ES SALAAM", "branch": null, "swift_code": "UNILTZTZXXX" },
{ "id": 84, "bank": "CANARA BANK (TANZANIA) LTD", "city": "DAR ES SALAAM", "branch": null, "swift_code": "CNRBTZTZXXX" },
{ "id": 85, "bank": "SABMILLER TANZANIA", "city": "DAR ES SALAAM", "branch": null, "swift_code": "SABMTZT1XXX" },
{ "id": 86, "bank": "SABMILLER TANZANIA", "city": "DAR ES SALAAM", "branch": null, "swift_code": "SABMTZT1TBL" },
{ "id": 87, "bank": "SABMILLER TANZANIA", "city": "DAR ES SALAAM", "branch": null, "swift_code": "SABMTZT1TDL" },
{ "id": 88, "bank": "STANDARD CHARTERED BANK TANZANIA LTD", "city": "DAR ES SALAAM", "branch": null, "swift_code": "SCBLTZTXXXX" },
{ "id": 89, "bank": "BANK OF AFRICA TANZANIA LIMITED", "city": "DAR ES SALAAM", "branch": null, "swift_code": "EUAFTZTZXXX" },
{ "id": 90, "bank": "GUARANTY TRUST BANK TANZANIA LTD", "city": "DAR ES SALAAM", "branch": null, "swift_code": "GTBITZTZXXX" },
{ "id": 91, "bank": "TWIGA BANCORP LIMITED", "city": "DAR ES SALAAM", "branch": null, "swift_code": "NABHTZT1XXX" },
{ "id": 92, "bank": "FINCA MICROFINANCE BANK LIMITED", "city": "DAR ES SALAAM", "branch": null, "swift_code": "FNMITZTZXXX" },
{ "id": 93, "bank": "TANZANIA AGRICULTURAL DEVELOPMENT BANK", "city": "DAR ES SALAAM", "branch": null, "swift_code": "TZADTZTZXXX" },
{ "id": 94, "bank": "YETU MICROFINANCE BANK PLC", "city": "DAR ES SALAAM", "branch": null, "swift_code": "YETMTZTZXXX" },
{ "id": 95, "bank": "BUSINESS CONNEXION (TANZANIA) LIMITED", "city": "DAR ES SALAAM", "branch": null, "swift_code": "BCTITZTTXXX" },
{ "id": 96, "bank": "CHINA DASHENG BANK LIMITED", "city": "DAR ES SALAAM", "branch": null, "swift_code": "CDSHTZTZXXX" }
    ]
}
